caselib.py
setup.py
caselib.egg-info/PKG-INFO
caselib.egg-info/SOURCES.txt
caselib.egg-info/dependency_links.txt
caselib.egg-info/top_level.txt