Metadata-Version: 1.1
Name: caselib
Version: 0.1.2
Summary: A string converter between different naming convention
Home-page: UNKNOWN
Author: Heungsub Lee
Author-email: h@subl.ee
License: BSD
Platform: any
Classifier: Development Status :: 4 - Beta
Classifier: Environment :: Console
Classifier: Intended Audience :: Developers
Classifier: License :: OSI Approved :: BSD License
Classifier: Operating System :: OS Independent
Classifier: Programming Language :: Python
Classifier: Topic :: Text Processing
Classifier: Topic :: Utilities
